motutils/__init__.py
motutils/__main__.py
motutils/bbox_mot.py
motutils/cli.py
motutils/io.py
motutils/mot.py
motutils/oracle_detector.py
motutils/posemot.py
motutils/via.py
motutils/visualize.py
motutils-0.1.2.dist-info/LICENSE
motutils-0.1.2.dist-info/METADATA
motutils-0.1.2.dist-info/WHEEL
motutils-0.1.2.dist-info/entry_points.txt
motutils-0.1.2.dist-info/top_level.txt
motutils-0.1.2.dist-info/zip-safe
motutils-0.1.2.dist-info/RECORD
