Metadata-Version: 2.1
Name: motutils
Version: 0.1.2
Summary: utilities for multiple object tracking research (io, visualization, format conversion)
Home-page: https://github.com/smidm/motutils
Author: Matěj Šmíd
Author-email: m@matejsmid.cz
License: MIT
Project-URL: Issue Tracker, https://github.com/smidm/motutils/issues
Platform: UNKNOWN
Classifier: Development Status :: 5 - Production/Stable
Classifier: Intended Audience :: Developers
Classifier: Intended Audience :: Science/Research
Classifier: License :: OSI Approved :: MIT License
Classifier: Operating System :: Unix
Classifier: Operating System :: POSIX
Classifier: Operating System :: Microsoft :: Windows
Classifier: Programming Language :: Python
Classifier: Programming Language :: Python :: 3
Classifier: Programming Language :: Python :: 3 :: Only
Classifier: Programming Language :: Python :: 3.6
Classifier: Programming Language :: Python :: 3.7
Classifier: Programming Language :: Python :: 3.8
Classifier: Programming Language :: Python :: 3.9
Classifier: Programming Language :: Python :: Implementation :: CPython
Classifier: Topic :: Utilities
Classifier: Topic :: Scientific/Engineering :: Artificial Intelligence
Requires-Python: >=3.6
License-File: LICENSE
Requires-Dist: click
Requires-Dist: h5py
Requires-Dist: matplotlib
Requires-Dist: motmetrics
Requires-Dist: moviepy
Requires-Dist: numpy
Requires-Dist: opencv-python-headless
Requires-Dist: pandas
Requires-Dist: scipy
Requires-Dist: tqdm
Requires-Dist: xarray
Requires-Dist: shape
Provides-Extra: sleap
Requires-Dist: sleap ; extra == 'sleap'
